AUTHORS.rst
CONTRIBUTING.rst
HISTORY.rst
LICENSE
MANIFEST.in
README.rst
setup.cfg
setup.py
dbus2any/__init__.py
dbus2any/__main__.py
dbus2any/args.py
dbus2any/dbus2xml.py
dbus2any/list.py
dbus2any/xml2any.py
dbus2any.egg-info/PKG-INFO
dbus2any.egg-info/SOURCES.txt
dbus2any.egg-info/dependency_links.txt
dbus2any.egg-info/not-zip-safe
dbus2any.egg-info/requires.txt
dbus2any.egg-info/top_level.txt
docs/Makefile
docs/authors.rst
docs/conf.py
docs/contributing.rst
docs/history.rst
docs/index.rst
docs/installation.rst
docs/make.bat
docs/readme.rst
docs/usage.rst
tests/__init__.py
tests/test_dbus2any.py
tests/expected/mpris2.py
tests/expected/openobex.py
tests/expected/pidgin.py
tests/xml/openobex.xml