Metadata-Version: 1.1
Name: dbus2any
Version: 0.1.0
Summary: convert dbus instrospection to code
Home-page: https://github.com/hugosenari/dbus2any
Author: Hugo Ribeiro
Author-email: hugosenari@gmail.com
License: ISCL
Keywords: dbus2any
Platform: UNKNOWN
Classifier: Development Status :: 2 - Pre-Alpha
Classifier: Intended Audience :: Developers
Classifier: License :: OSI Approved :: ISC License (ISCL)
Classifier: Natural Language :: English
Classifier: Programming Language :: Python :: 2
Classifier: Programming Language :: Python :: 2.6
Classifier: Programming Language :: Python :: 2.7
Classifier: Programming Language :: Python :: 3
Classifier: Programming Language :: Python :: 3.3
Classifier: Programming Language :: Python :: 3.4
